clangtags/__main__.py
clangtags/py.typed
clangtags/tag_and_syntax.py
clangtags/typed.py
clangtags/clang/cindex.py
clangtags/clang/enumerations.py
clangtags/clang/py.typed
clangtags-0.1.dev0.dist-info/METADATA
clangtags-0.1.dev0.dist-info/WHEEL
clangtags-0.1.dev0.dist-info/top_level.txt
clangtags-0.1.dev0.dist-info/RECORD
